CHANGES
LICENSE
MANIFEST.in
README.rst
setup.py
django_leaflet_cadasta.egg-info/PKG-INFO
django_leaflet_cadasta.egg-info/SOURCES.txt
django_leaflet_cadasta.egg-info/dependency_links.txt
django_leaflet_cadasta.egg-info/not-zip-safe
django_leaflet_cadasta.egg-info/requires.txt
django_leaflet_cadasta.egg-info/top_level.txt
leaflet/__init__.py
leaflet/admin.py
leaflet/apps.py
leaflet/models.py
leaflet/utils.py
leaflet/forms/__init__.py
leaflet/forms/backport.py
leaflet/forms/fields.py
leaflet/forms/nogeos.py
leaflet/forms/widgets.py
leaflet/locale/cs/LC_MESSAGES/django.mo
leaflet/locale/de/LC_MESSAGES/django.mo
leaflet/locale/es/LC_MESSAGES/django.mo
leaflet/locale/fr/LC_MESSAGES/django.mo
leaflet/locale/he/LC_MESSAGES/django.mo
leaflet/locale/it/LC_MESSAGES/django.mo
leaflet/static/leaflet/Control.MiniMap.css
leaflet/static/leaflet/Control.MiniMap.js
leaflet/static/leaflet/eventlistener.ie6-7.js
leaflet/static/leaflet/eventlistener.ie8.js
leaflet/static/leaflet/leaflet-src.js
leaflet/static/leaflet/leaflet.css
leaflet/static/leaflet/leaflet.extras.js
leaflet/static/leaflet/leaflet.forms.js
leaflet/static/leaflet/leaflet.ie.css
leaflet/static/leaflet/leaflet.js
leaflet/static/leaflet/proj4js.js
leaflet/static/leaflet/proj4leaflet.js
leaflet/static/leaflet/draw/leaflet.draw-src.css
leaflet/static/leaflet/draw/leaflet.draw-src.js
leaflet/static/leaflet/draw/leaflet.draw.css
leaflet/static/leaflet/draw/leaflet.draw.js
leaflet/static/leaflet/draw/images/layers-2x.png
leaflet/static/leaflet/draw/images/layers.png
leaflet/static/leaflet/draw/images/marker-icon-2x.png
leaflet/static/leaflet/draw/images/marker-icon.png
leaflet/static/leaflet/draw/images/marker-shadow.png
leaflet/static/leaflet/draw/images/spritesheet-2x.png
leaflet/static/leaflet/draw/images/spritesheet.png
leaflet/static/leaflet/draw/images/spritesheet.svg
leaflet/static/leaflet/images/layers-2x.png
leaflet/static/leaflet/images/layers.png
leaflet/static/leaflet/images/marker-icon-2x.png
leaflet/static/leaflet/images/marker-icon.png
leaflet/static/leaflet/images/marker-icon@2x.png
leaflet/static/leaflet/images/marker-shadow.png
leaflet/static/leaflet/images/reset-view.png
leaflet/static/leaflet/images/toggle.png
leaflet/static/leaflet/images/zoom-in.png
